retico
